HotReload/HotReload.py
HotReload/__init__.py
HotReload/main.py
universal_hotreload_python-0.1.2.dist-info/licenses/LICENSE
universal_hotreload_python-0.1.2.dist-info/METADATA
universal_hotreload_python-0.1.2.dist-info/WHEEL
universal_hotreload_python-0.1.2.dist-info/entry_points.txt
universal_hotreload_python-0.1.2.dist-info/top_level.txt
universal_hotreload_python-0.1.2.dist-info/RECORD
